{
  "meta": {
    "version": "1.1",
    "description": "Translation glossary for IT→EN and IT→FR. Terms must be translated consistently across all pages.",
    "lastUpdated": "2026-02-18"
  },
  "terms": {
    "permesso di soggiorno": "residence permit",
    "permesso": "permit",
    "Questura": "Police Headquarters (Questura)",
    "Prefettura": "Prefecture",
    "soggiornante di lungo periodo": "long-term resident",
    "decreto flussi": "annual immigration quota decree",
    "kit postale": "postal kit",
    "primo rilascio": "first issue",
    "rinnovo": "renewal",
    "richiesta asilo": "asylum application",
    "protezione internazionale": "international protection",
    "protezione sussidiaria": "subsidiary protection",
    "protezione speciale": "special protection",
    "status di rifugiato": "refugee status",
    "ricongiungimento familiare": "family reunification",
    "coesione familiare": "family cohesion",
    "motivi familiari": "family reasons",
    "lavoro subordinato": "employed work",
    "lavoro autonomo": "self-employment",
    "attesa occupazione": "job seeking",
    "ricerca lavoro": "job search",
    "Commissione Territoriale": "Territorial Commission",
    "Servizio Sanitario Nazionale": "National Health Service",
    "SSN": "NHS (SSN)",
    "marca da bollo": "revenue stamp",
    "bollettino postale": "postal payment slip",
    "codice fiscale": "tax code",
    "carta d'identità": "ID card",
    "dichiarazione ospitalità": "hospitality declaration",
    "contratto di affitto": "rental contract",
    "cittadino UE": "EU citizen",
    "cittadino italiano": "Italian citizen",
    "extracomunitario": "non-EU citizen",
    "minore": "minor",
    "maggiorenne": "adult",
    "visto di ingresso": "entry visa",
    "permesso giallo": "yellow permit",
    "carta di soggiorno": "residence card"
  },
  "termsFr": {
    "permesso di soggiorno": "titre de séjour",
    "permesso": "titre de séjour",
    "Questura": "Questure (commissariat principal)",
    "Prefettura": "Préfecture",
    "soggiornante di lungo periodo": "résident de longue durée",
    "decreto flussi": "décret annuel sur les quotas d'immigration",
    "kit postale": "kit postal",
    "primo rilascio": "première délivrance",
    "rinnovo": "renouvellement",
    "richiesta asilo": "demande d'asile",
    "protezione internazionale": "protection internationale",
    "protezione sussidiaria": "protection subsidiaire",
    "protezione speciale": "protection spéciale",
    "status di rifugiato": "statut de réfugié",
    "ricongiungimento familiare": "regroupement familial",
    "coesione familiare": "cohésion familiale",
    "motivi familiari": "motifs familiaux",
    "lavoro subordinato": "travail salarié",
    "lavoro autonomo": "travail indépendant",
    "attesa occupazione": "recherche d'emploi",
    "ricerca lavoro": "recherche d'emploi",
    "Commissione Territoriale": "Commission territoriale",
    "Servizio Sanitario Nazionale": "Service national de santé (SSN)",
    "SSN": "SSN (Sécurité sociale italienne)",
    "marca da bollo": "timbre fiscal",
    "bollettino postale": "bordereau de paiement postal",
    "codice fiscale": "code fiscal",
    "carta d'identità": "carte d'identité",
    "dichiarazione ospitalità": "déclaration d'hébergement",
    "contratto di affitto": "contrat de location",
    "cittadino UE": "citoyen UE",
    "cittadino italiano": "citoyen italien",
    "extracomunitario": "ressortissant non-UE",
    "minore": "mineur",
    "maggiorenne": "majeur",
    "visto di ingresso": "visa d'entrée",
    "permesso giallo": "récépissé (permesso giallo)",
    "carta di soggiorno": "carte de séjour"
  },
  "doNotTranslate": [
    "SOS Permesso",
    "Typeform",
    "Schengen",
    "D.Lgs.",
    "D.P.R.",
    "art.",
    "comma"
  ],
  "uiStrings": {
    "Tutti i permessi": "All permits",
    "Che documenti porto in Questura": "What documents to bring to the Police",
    "Posso AVERE un permesso?": "Can I GET a permit?",
    "Posso CONVERTIRE?": "Can I CONVERT?",
    "Posso RINNOVARE il permesso?": "Can I RENEW my permit?",
    "Dai una mano": "Help out",
    "Segnala un errore": "Report an error",
    "Dai un feedback": "Give feedback",
    "Scrivici": "Contact us",
    "Potrebbero interessarti anche": "You might also be interested in",
    "Documenti Questura": "Police Documents",
    "Dizionario": "Dictionary",
    "Il Progetto": "The Project",
    "Chi Siamo": "About Us",
    "Privacy Policy": "Privacy Policy",
    "Contatti": "Contact",
    "Documenti per il primo rilascio": "Documents for first issue",
    "Documenti per il rinnovo": "Documents for renewal",
    "Documenti necessari": "Required documents",
    "Segnala errore": "Report error",
    "Fai il nostro test": "Take our test",
    "Hai altre domande": "Do you have more questions",
    "Non trovi il permesso che cercavi?": "Can't find the permit you're looking for?",
    "Scrivici per aiuto": "Contact us for help",
    "Vedi anche": "See also",
    "Completati": "Completed",
    "Spunta i documenti che hai già preparato": "Check off the documents you've already prepared",
    "I tuoi progressi vengono salvati automaticamente": "Your progress is saved automatically",
    "Nota": "Note",
    "Attenzione": "Warning",
    "Invia tramite KIT alle Poste": "Submit via postal KIT (no Police visit needed)"
  }
}
